LICENSE
README.rst
pyproject.toml
setup.cfg
setup.py
drf_api_lens/__init__.py
drf_api_lens/admin.py
drf_api_lens/apps.py
drf_api_lens/decorators.py
drf_api_lens/middleware.py
drf_api_lens/models.py
drf_api_lens/store_capture_error.py
drf_api_lens/tests.py
drf_api_lens/utils.py
drf_api_lens/validators.py
drf_api_lens/views.py
drf_api_lens.egg-info/PKG-INFO
drf_api_lens.egg-info/SOURCES.txt
drf_api_lens.egg-info/dependency_links.txt
drf_api_lens.egg-info/top_level.txt
drf_api_lens/migrations/0001_initial.py
drf_api_lens/migrations/__init__.py