Metadata-Version: 2.1
Name: drf-api-lens
Version: 1.0
Summary: DRF API Lens is a comprehensive Python package designed to help developers capture errors in their Django REST framework (DRF) APIs.
Home-page: https://github.com/pragnesh123-cmd/drf_api_lens
Author: Pragnesh Patel
Author-email: patelpragnesh386@gmail.com
License: BSD-3-Clause
Platform: UNKNOWN
Classifier: Environment :: Web Environment
Classifier: Framework :: Django
Classifier: Intended Audience :: Developers
Classifier: License :: OSI Approved :: BSD License
Classifier: Operating System :: OS Independent
Classifier: Programming Language :: Python
Classifier: Topic :: Internet :: WWW/HTTP
Classifier: Topic :: Internet :: WWW/HTTP :: Dynamic Content
License-File: LICENSE
